zorg-0.0.5.dist-info/RECORD
zorg-0.0.5.dist-info/top_level.txt
zorg-0.0.5.dist-info/metadata.json
zorg-0.0.5.dist-info/zip-safe
zorg-0.0.5.dist-info/METADATA
zorg-0.0.5.dist-info/DESCRIPTION.rst
zorg-0.0.5.dist-info/WHEEL
zorg/utils.py
zorg/connection.py
zorg/test.py
zorg/robot.py
zorg/api.py
zorg/adaptor.py
zorg/__init__.py
zorg/main.py
zorg/driver.py
zorg/device.py
