Metadata-Version: 2.0
Name: zorg
Version: 0.0.5
Summary: Python framework for robotics and physical computing.
Home-page: https://github.com/zorg/zorg
Author: Zorg Group
Author-email: gunthercx@gmail.com
License: MIT
Keywords: zorg,robotics
Platform: any
Classifier: Development Status :: 4 - Beta
Classifier: Intended Audience :: Developers
Classifier: License :: OSI Approved :: BSD License
Classifier: Environment :: Console
Classifier: Environment :: Web Environment
Classifier: Operating System :: OS Independent
Classifier: Programming Language :: Python
Classifier: Programming Language :: Python :: 2
Classifier: Programming Language :: Python :: 2.7
Classifier: Programming Language :: Python :: 3
Classifier: Programming Language :: Python :: 3.3
Classifier: Programming Language :: Python :: 3.4
